darca_git/__init__.py
darca_git/__version__.py
darca_git/git.py
darca_git-0.1.0.dist-info/LICENSE
darca_git-0.1.0.dist-info/METADATA
darca_git-0.1.0.dist-info/WHEEL
darca_git-0.1.0.dist-info/RECORD
